youcanpay_python/__init__.py
youcanpay_python/adapters/__init__.py
youcanpay_python/adapters/adapter_picker.py
youcanpay_python/adapters/http_adapters.py
youcanpay_python/api/__init__.py
youcanpay_python/api/endpoints.py
youcanpay_python/api/service.py
youcanpay_python/exceptions/__init__.py
youcanpay_python/exceptions/exceptions.py
youcanpay_python/models/__init__.py
youcanpay_python/models/data.py
youcanpay_python/models/token.py
youcanpay_python/youcan_pay.py
youcanpay_python-0.1.0.dist-info/LICENSE
youcanpay_python-0.1.0.dist-info/METADATA
youcanpay_python-0.1.0.dist-info/WHEEL
youcanpay_python-0.1.0.dist-info/RECORD
